{"type":"footer","name":"Footer","sections":{"footer":{"type":"footer","blocks":{"footer-2":{"type":"text","settings":{"image":"shopify:\/\/shop_images\/logo_header.png","image_width":180,"title":"","text":"<p>7901 4th St N, St. Petersburg, FL, US, 33702<\/p><p>contact@miamitripbags.com<\/p><p>+1 (213) 650-4464<\/p>","column_width":22}},"footer-1":{"type":"linklist","settings":{"linklist":"quick-links","title":"","column_width":22}},"linklist_DTUB4j":{"type":"linklist","settings":{"linklist":"footer","title":"","column_width":22}},"footer-0":{"type":"newsletter","settings":{"title":"Join Miami Trip Bags","text":"<p>Subscribe to our newsletter and get 10% off your first purchase<\/p>","show_name":false,"button_text":"Join","show_arrow":true,"terms":false,"button_type":"btn--black","button_size":"","button_style":"btn--solid","show_social_links":false,"column_width":33}}},"block_order":["footer-2","footer-1","linklist_DTUB4j","footer-0"],"settings":{"logo":"{{ shop.brand.logo }}","logo_image_width":150,"overlay_opacity":75,"overlay_color":"#ffffff","padding_top":75,"padding_bottom":30}},"supporting-menu":{"type":"section-supporting-menu","settings":{"linklist":"","footer_payment_enable":false,"show_locale_selector":true,"show_currency_selector":true,"type":"currency","padding_top":30,"padding_bottom":30}}},"order":["footer","supporting-menu"]}